Workbook

Sheet Usuarios
A1: ID Usuario | B1: Rol | C1: Nombre(s) | D1: Apellido Paterno | E1: Apellido Materno | F1: Correo | G1: Contraseña | H1: Salt | I1: Hash
A2: 1 | B2: Administrador | C2: Dulce Ivonne | D2: Ugarte | E2: Gomez | F2: info@igo2.travel | G2: ******** | H2: 45e26402-94bc-4e15-a808-d583780c4e2f | I2: a465a562c42726b094030ab0f6abe758d0afbec82ba5c203ef922f0bc77b3c62

Sheet Clientes
A1: ID Cliente | B1: Nombre Completo | C1: Razón Social | D1: Tipo Persona | E1: RFC | F1: ID Usuario | G1: País | H1: Estado | I1: Ciudad | J1: Colonia | K1: Calle | L1: Número Exterior | M1: Número Interior | N1: CP | O1: Lada | P1: Teléfono | Q1: Correo | R1: Token Invitacion | S1: Lista Telefonos
A2: 1 | B2: JESUS LICEA REYES | D2: Física | O2: 52 | R2: 2002d9b9-77cc-47bf-a192-42bf799b7e7c | S2: [{"tipo":"Móvil","lada":"52","numero":""}]

Sheet CuentasEmpresa
A1: ID | B1: Nombre | C1: Tipo | D1: Banco | E1: Cuenta
A2: 1 | B2: CONCENTRADORA | C2: Banco | D2: CONCENTRADORA
A3: 2 | B3: INVEX 2.0 | C3: Banco | D3: INVEX 2.0

Sheet Pasajeros
A1: ID Pasajero | B1: ID Cliente | C1: Nombre(s) | D1: Apellido Paterno | E1: Apellido Materno | F1: Nacionalidad | G1: Fecha de Nacimiento | H1: ID Pasaporte | I1: ID Visa | J1: País | K1: Estado | L1: Ciudad | M1: Colonia | N1: Calle | O1: Número Exterior | P1: Número Interior | Q1: CP | R1: Lada | S1: Teléfono | T1: Correo | U1: Token Invitacion | V1: ID Usuario | W1: Lista Telefonos
A2: 1 | B2: 1 | C2: JESUS | D2: LICEA | E2: REYES | F2: 1 | G2: 23618 | R2: 52 | S2: 5541440849 | W2: [{"tipo":"Móvil","lada":"52","numero":"5541440849"}]
A3: 2 | B3: 1 | C3: SOCORRO | D3: SANTANA | E3: PANIAGUAA | F3: 1 | G3: 23961 | H3: 12345 | I3: 122564 | J3: 1 | K3: Ciudad de México | L3: Alvaro Obregon | M3: Lomas de Guadalupe | N3: Lechuzas | O3: 36 | Q3: 01720 | R3: 52 | S3: 5552150020 | T3: igza24@gmail.com | W3: [{"tipo":"Móvil","lada":"52","numero":"5552150020"}]

Sheet Viajes
A1: ID Viaje | B1: Nombre Viaje | C1: Tipo de Viaje | D1: ID Cliente | E1: Fecha Inicio | F1: Fecha Fin | G1: Calificación | H1: Comentarios
A2: I2-6015-1 | B2: I2-6015 Acapulco abr26 | C2: 1 | D2: 1 | E2: 46113 | F2: 46116

Sheet Transacciones
A1: ID Cliente | B1: ID Pasajero | C1: ID Viaje | D1: ID Servicio | E1: Fecha Transacción | F1: Tipo de Transacción | G1: Forma de Pago | H1: Proveedor | I1: Concepto | J1: Monto | K1: Moneda | L1: Tipo de Cambio | M1: Cuenta Empresa | N1: Subtotal | O1: Monto IVA | P1: Tasa IVA | Q1: No. Factura
E2: 46023 | F2: 2 | G2: 5 | H2: 16 | I2: Google Workspace ene26 | J2: 162.4 | K2: 1 | L2: 1 | N2: 140 | O2: 22.4 | P2: 16
C3: I2-6015-1 | D3: 1 | E3: 46070 | F3: 2 | G3: 5 | H3: 3 | I3: VUELO | J3: 12130 | K3: 1 | L3: 1 | M3: 2
A4: 1 | C4: I2-6015-1 | E4: 46070 | F4: 3 | G4: 3 | I4: ANTICIPO PAQUETE | J4: 13000 | K4: 1 | L4: 1 | M4: 1
A5: 1 | C5: I2-6015-1 | D5: 1 | E5: 46070 | F5: 1 | G5: 4 | I5: VUELO | J5: 12994 | K5: 1 | L5: 1

Sheet Servicios
A1: ID Servicio | B1: ID Cliente | C1: ID Viaje | D1: ID Pasajero | E1: Categoria | F1: Destino | G1: Clave de Reservación | H1: Fecha Inicio del Servicio | I1: Fecha Fin del Servicio | J1: Estatus | K1: Calificación | L1: Comentarios | M1: Costo Proveedor | N1: Precio Venta | O1: ID Proveedor
A2: 1 | B2: 1 | C2: I2-6015-1 | D2: 1 | E2: 1 | F2: MEX-ACA-MEX | G2: HYNDYI | H2: 46113.335 | I2: 46116.774 | J2: 1 | M2: 6065 | N2: 6497 | O2: 3
A3: 1 | B3: 1 | C3: I2-6015-1 | D3: 2 | E3: 1 | F3: MEX-ACA-MEX | G3: HYNDYI | H3: 46113.335 | I3: 46116.774 | J3: 1 | M3: 6065 | N3: 6497 | O3: 3
A4: 2 | B4: 1 | C4: I2-6015-1 | D4: 1 | E4: 3 | F4: AEROPUERTO-HOTEL | G4: T2876176 | J4: 1 | M4: 432 | N4: 480 | O4: 4
A5: 3 | B5: 1 | C5: I2-6015-1 | D5: 1 | E5: 2 | F5: CAMINO REAL AEROPUERTO MEXICO | G5: 71-6643258 | H5: 46113.625 | I5: 46114.5 | J5: 1 | M5: 2457.51 | N5: 2857.37 | O5: 5
A6: 4 | B6: 1 | C6: I2-6015-1 | D6: 1 | E6: 2 | F6: PALACIO MUNDO IMPERIAL | G6: 71-6643258 | H6: 46114.625 | I6: 46116 | J6: 1 | M6: 11576.29 | N6: 13460.8 | O6: 5
A7: 5 | B7: 1 | C7: I2-6015-1 | D7: 1 | E7: 3 | F7: HOTEL-AEROPUERTO | G7: T2876177 | H7: 46116.667 | I7: 46116.688 | J7: 1 | M7: 432 | N7: 480 | O7: 4

Sheet Proveedores
A1: ID Proveedor | B1: Nombre Completo | C1: Razón Social | D1: RFC | E1: País | F1: Ciudad | G1: Colonia | H1: Calle | I1: Número Exterior | J1: Número Interior | K1: CP | L1: Lada | M1: Teléfono | N1: Correo | O1: Lista Telefonos
A2: 1 | B2: GOOGLE | C2: GOOGLE CLOUD MEXICO | D2: GCM221031837 | F2: MIGUEL HIDALGO | G2: LOMAS DE CHAPULTEPEC | H2: MONTES URALES | I2: 445 | J2: 5 | K2: 11000 | L2: 52 | M2: 5553428400
A3: 2 | B3: Mex Rent a Car | L3: 52 | O3: [{"tipo":"Oficina","lada":"52","numero":""}]
A4: 3 | B4: VOLARIS | C4: CONCESIONARIA VUELA | L4: 52 | O4: [{"tipo":"Oficina","lada":"52","numero":""}]
A5: 4 | B5: CIVITATIS | L5: 52 | O5: [{"tipo":"Oficina","lada":"52","numero":""}]
A6: 5 | B6: BOL | C6: BEDS ONLINE | L6: 52 | O6: [{"tipo":"Oficina","lada":"52","numero":""}]

Sheet Saldo a Favor
A1: ID Cliente | B1: Saldo
A2: =IFERROR(__xludf.DUMMYFUNCTION("UNIQUE(FILTER(Transacciones[ID Cliente],Transacciones[Tipo de Transacción]=Listas!$H$5))"),1.0) -> 1 | B2: =IF(A2="","", SUMIFS(Transacciones[Monto], Transacciones[ID Cliente], 'Saldo a Favor'!$A2, Transacciones[Tipo de Transacción], Listas!$H$5) - SUMIFS(Transacciones[Monto], Transacciones[ID Cliente], 'Saldo a Favor'!$A2, Transacciones[Tipo de Transacción], Listas!$H$3, Transacciones[Forma de Pago], Listas!$K$6)) -> 6
B3: =IF(A3="","", SUMIFS(Transacciones[Monto], Transacciones[ID Cliente], 'Saldo a Favor'!$A3, Transacciones[Tipo de Transacción], Listas!$H$5) - SUMIFS(Transacciones[Monto], Transacciones[ID Cliente], 'Saldo a Favor'!$A3, Transacciones[Tipo de Transacción], Listas!$H$3, Transacciones[Forma de Pago], Listas!$K$6))
B4: =IF(A4="","", SUMIFS(Transacciones[Monto], Transacciones[ID Cliente], 'Saldo a Favor'!$A4, Transacciones[Tipo de Transacción], Listas!$H$5) - SUMIFS(Transacciones[Monto], Transacciones[ID Cliente], 'Saldo a Favor'!$A4, Transacciones[Tipo de Transacción], Listas!$H$3, Transacciones[Forma de Pago], Listas!$K$6))
B5: =IF(A5="","", SUMIFS(Transacciones[Monto], Transacciones[ID Cliente], 'Saldo a Favor'!$A5, Transacciones[Tipo de Transacción], Listas!$H$5) - SUMIFS(Transacciones[Monto], Transacciones[ID Cliente], 'Saldo a Favor'!$A5, Transacciones[Tipo de Transacción], Listas!$H$3, Transacciones[Forma de Pago], Listas!$K$6))
B6: =IF(A6="","", SUMIFS(Transacciones[Monto], Transacciones[ID Cliente], 'Saldo a Favor'!$A6, Transacciones[Tipo de Transacción], Listas!$H$5) - SUMIFS(Transacciones[Monto], Transacciones[ID Cliente], 'Saldo a Favor'!$A6, Transacciones[Tipo de Transacción], Listas!$H$3, Transacciones[Forma de Pago], Listas!$K$6))
B7: =IF(A7="","", SUMIFS(Transacciones[Monto], Transacciones[ID Cliente], 'Saldo a Favor'!$A7, Transacciones[Tipo de Transacción], Listas!$H$5) - SUMIFS(Transacciones[Monto], Transacciones[ID Cliente], 'Saldo a Favor'!$A7, Transacciones[Tipo de Transacción], Listas!$H$3, Transacciones[Forma de Pago], Listas!$K$6))
B8: =IF(A8="","", SUMIFS(Transacciones[Monto], Transacciones[ID Cliente], 'Saldo a Favor'!$A8, Transacciones[Tipo de Transacción], Listas!$H$5) - SUMIFS(Transacciones[Monto], Transacciones[ID Cliente], 'Saldo a Favor'!$A8, Transacciones[Tipo de Transacción], Listas!$H$3, Transacciones[Forma de Pago], Listas!$K$6))
B9: =IF(A9="","", SUMIFS(Transacciones[Monto], Transacciones[ID Cliente], 'Saldo a Favor'!$A9, Transacciones[Tipo de Transacción], Listas!$H$5) - SUMIFS(Transacciones[Monto], Transacciones[ID Cliente], 'Saldo a Favor'!$A9, Transacciones[Tipo de Transacción], Listas!$H$3, Transacciones[Forma de Pago], Listas!$K$6))
B10: =IF(A10="","", SUMIFS(Transacciones[Monto], Transacciones[ID Cliente], 'Saldo a Favor'!$A10, Transacciones[Tipo de Transacción], Listas!$H$5) - SUMIFS(Transacciones[Monto], Transacciones[ID Cliente], 'Saldo a Favor'!$A10, Transacciones[Tipo de Transacción], Listas!$H$3, Transacciones[Forma de Pago], Listas!$K$6))
B11: =IF(A11="","", SUMIFS(Transacciones[Monto], Transacciones[ID Cliente], 'Saldo a Favor'!$A11, Transacciones[Tipo de Transacción], Listas!$H$5) - SUMIFS(Transacciones[Monto], Transacciones[ID Cliente], 'Saldo a Favor'!$A11, Transacciones[Tipo de Transacción], Listas!$H$3, Transacciones[Forma de Pago], Listas!$K$6))
B12: =IF(A12="","", SUMIFS(Transacciones[Monto], Transacciones[ID Cliente], 'Saldo a Favor'!$A12, Transacciones[Tipo de Transacción], Listas!$H$5) - SUMIFS(Transacciones[Monto], Transacciones[ID Cliente], 'Saldo a Favor'!$A12, Transacciones[Tipo de Transacción], Listas!$H$3, Transacciones[Forma de Pago], Listas!$K$6))
B13: =IF(A13="","", SUMIFS(Transacciones[Monto], Transacciones[ID Cliente], 'Saldo a Favor'!$A13, Transacciones[Tipo de Transacción], Listas!$H$5) - SUMIFS(Transacciones[Monto], Transacciones[ID Cliente], 'Saldo a Favor'!$A13, Transacciones[Tipo de Transacción], Listas!$H$3, Transacciones[Forma de Pago], Listas!$K$6))
B14: =IF(A14="","", SUMIFS(Transacciones[Monto], Transacciones[ID Cliente], 'Saldo a Favor'!$A14, Transacciones[Tipo de Transacción], Listas!$H$5) - SUMIFS(Transacciones[Monto], Transacciones[ID Cliente], 'Saldo a Favor'!$A14, Transacciones[Tipo de Transacción], Listas!$H$3, Transacciones[Forma de Pago], Listas!$K$6))
... B443: =IF(A443="","", SUMIFS(Transacciones[Monto], Transacciones[ID Cliente], 'Saldo a Favor'!$A443, Transacciones[Tipo de Transacción], Listas!$H$5) - SUMIFS(Transacciones[Monto], Transacciones[ID Cliente], 'Saldo a Favor'!$A443, Transacciones[Tipo de Transacción], Listas!$H$3, Transacciones[Forma de Pago], Listas!$K$6))

Sheet Configuracion
A1: Clave | B1: Valor | C1: Notas
A2: color_primario | B2: #009688 | C2: Es para los colores de los botones y ciertas partes de la app
A3: nombre_empresa | B3: IGO2TRAVEL | C3: Lo que saldra en el texto del login
A4: logo_url | B4: https://i.postimg.cc/x866JRqT/7fc495df-83d1-42f9-9c3d-bfa08cddb8f6.jpg | C4: el logo que sale en el recuadro, recuerda poner una imagen 90x90
A5: app_ico_url | B5: https://i.postimg.cc/cHrXpVCX/logo192.png

Sheet Listas
A1: Tipo de Viaje | D1: Categoría | G1: Tipo de Transacción | J1: Forma de Pago | N1: Países | R1: Nacionalidades | U1: Tipo de Cambio | Z1: Estatus | AC1: Calificación
A2: Tipo | B2: ID | D2: Categoría | E2: ID | G2: Tipo | H2: ID | J2: Tipo | K2: ID | L2: Comisión | N2: País | O2: ID | P2: Lada | R2: Nacionalidad | S2: ID | U2: Moneda | V2: vs | W2: Tipo Cambio | X2: ID | Z2: Estatus | AA2: ID | AC2: 0
A3: Vacacional | B3: 1 | D3: Vuelo | E3: 1 | G3: Ingreso | H3: 1 | J3: Clip | K3: 1 | L3: ((0.036)*1.16) | N3: México | O3: 1 | P3: =+52 -> 52 | R3: Mexicana | S3: 1 | U3: MXN | V3: MXN | W3: 1 | X3: 1 | Z3: Cotizado | AA3: 1 | AC3: 0.1
A4: Negocios | B4: 2 | D4: Hospedaje | E4: 2 | G4: Egreso | H4: 2 | J4: Efectivo | K4: 2 | L4: 0 | N4: Estados Unidos | O4: 2 | P4: =+1 -> 1 | R4: Estado Unidense | S4: 2 | U4: USD | V4: USD/MXN | W4: 18.02 | X4: 2 | Z4: Realizado | AA4: 2 | AC4: 0.2
D5: Traslado | E5: 3 | G5: Abono | H5: 3 | J5: Transferencia | K5: 3 | L5: 0 | N5: Brasil | O5: 3 | P5: =+55 -> 55 | R5: Basileña | S5: 3 | U5: BRL | V5: BRL/MXN | W5: 3.25 | X5: 3 | Z5: Cancelado | AA5: 3 | AC5: 0.3
D6: Alimentos | E6: 4 | J6: Saldo | K6: 4 | L6: 0 | U6: EUR | V6: EUR/MXN | W6: 21.0912 | X6: 4 | Z6: Confirmado | AA6: 4 | AC6: 0.4
D7: Tour | E7: 5 | J7: Tarjeta | K7: 5 | L7: 0 | AC7: 0.5
D8: Crucero | E8: 6 | AC8: 0.6
D9: Renta auto | E9: 7 | AC9: 0.7
AC10: 0.8
AC11: 0.9
AC12: 1
AC13: 1.1
AC14: 1.2
AC15: 1.3
AC16: 1.4
AC17: 1.5
AC18: 1.6
AC19: 1.7
AC20: 1.8
AC21: 1.9
... AC52: 5

Sheet Roles
A1: ID Rol | B1: Nombre Rol | C1: Nivel Acceso
A2: 1 | B2: Administrador | C2: 10 | D2: Acceso total al sistema
A3: 2 | B3: Pasajero | C3: 1 | D3: Solo ve sus viajes y perfil
A4: 3 | B4: Cliente | C4: 5 | D4: (Futuro: Ver solo sus pasajeros asignados)
